subproxy/__init__.py
subproxy/subproxy.py
subproxy-0.0.4.dist-info/LICENSE.txt
subproxy-0.0.4.dist-info/METADATA
subproxy-0.0.4.dist-info/WHEEL
subproxy-0.0.4.dist-info/top_level.txt
subproxy-0.0.4.dist-info/RECORD
