Metadata-Version: 2.1
Name: subproxy
Version: 0.0.4
Summary: General Subprocess Proxy Object
Home-page: https://github.com/yycho0108/Subproxy
Author: Yoonyoung Cho
Author-email: jchocholate@gmail.com
License: MIT
Download-URL: https://github.com/yycho0108/Subproxy
Keywords: multiprocessing,proxy
Platform: Linux
Classifier: Development Status :: 1 - Planning
Classifier: Programming Language :: Python :: 3
Classifier: Programming Language :: Python :: 3.6
Classifier: Programming Language :: Python :: 3.7
Classifier: Intended Audience :: Developers
Classifier: License :: OSI Approved :: MIT License
Requires-Python: >=3.6
